LICENCE
MANIFEST.in
README.rst
raven_harakiri.py
setup.py
raven_harakiri.egg-info/PKG-INFO
raven_harakiri.egg-info/SOURCES.txt
raven_harakiri.egg-info/dependency_links.txt
raven_harakiri.egg-info/entry_points.txt
raven_harakiri.egg-info/requires.txt
raven_harakiri.egg-info/top_level.txt