Metadata-Version: 1.0
Name: raven-harakiri
Version: 0.1.2
Summary: Send UWSGI harakiri logs to sentry
Home-page: http://github.com/futurecolors/raven-harakiri
Author: Ilya Baryshev
Author-email: baryshev@gmail.com
License: MIT
Platform: UNKNOWN
Classifier: Development Status :: 3 - Alpha
Classifier: Intended Audience :: Developers
Classifier: License :: OSI Approved :: MIT License
Classifier: Operating System :: OS Independent
Classifier: Programming Language :: Python
Classifier: Programming Language :: Python :: 2.6
Classifier: Programming Language :: Python :: 2.7
